Final_library/__init__.py
Final_library/algorithms.py
Final_library/utils.py
Final_library_of_optimization_problems-0.0.2.dist-info/METADATA
Final_library_of_optimization_problems-0.0.2.dist-info/WHEEL
Final_library_of_optimization_problems-0.0.2.dist-info/top_level.txt
Final_library_of_optimization_problems-0.0.2.dist-info/RECORD
