Metadata-Version: 2.1
Name: Final-library-of-optimization-problems
Version: 0.0.2
Summary: A package with optimization functions
Home-page: https://github.com/Romzezz/Final_library_of_optimization_problems/
Author: Daniil Belotserkovskiy
License: UNKNOWN
Platform: UNKNOWN
Classifier: Programming Language :: Python :: 3.7
Classifier: License :: OSI Approved :: GNU General Public License v3 (GPLv3)
Requires-Dist: ipython (>=6)
Requires-Dist: nbformat (>=4)
Requires-Dist: nbconvert (>=5)
Requires-Dist: requests (>=2)
